{
  "task_id": "TASK-GR6-007",
  "checkpoints": [
    {
      "turn": 1,
      "commit_hash": "26ec0e9e2f99933aa8065456363e9ca87c23bc35",
      "timestamp": "2026-02-01T17:06:54.384004",
      "tests_passed": false,
      "test_count": 0,
      "message": "[guardkit-checkpoint] Turn 1 complete (tests: fail)"
    },
    {
      "turn": 2,
      "commit_hash": "a497295b2f60560441e52ba05bd2dad061f8eac5",
      "timestamp": "2026-02-01T17:08:24.215627",
      "tests_passed": false,
      "test_count": 0,
      "message": "[guardkit-checkpoint] Turn 2 complete (tests: fail)"
    },
    {
      "turn": 3,
      "commit_hash": "4187f1369745cb25a06d87041f8c435cfb43ba48",
      "timestamp": "2026-02-01T17:13:57.580005",
      "tests_passed": false,
      "test_count": 0,
      "message": "[guardkit-checkpoint] Turn 3 complete (tests: fail)"
    },
    {
      "turn": 4,
      "commit_hash": "03fad16c7e47ac902b3ba2c3bd4591568a8a3880",
      "timestamp": "2026-02-01T17:17:03.166299",
      "tests_passed": false,
      "test_count": 0,
      "message": "[guardkit-checkpoint] Turn 4 complete (tests: fail)"
    },
    {
      "turn": 5,
      "commit_hash": "215c8ff6dece6b6ba17a37b69f032c970adf40ae",
      "timestamp": "2026-02-01T17:20:23.436440",
      "tests_passed": false,
      "test_count": 0,
      "message": "[guardkit-checkpoint] Turn 5 complete (tests: fail)"
    }
  ],
  "last_updated": "2026-02-01T17:20:23.436622"
}